[
  {
    "id": "1737670734567-NACION-Previa",
    "fecha": "23/01/2025",
    "dia": "jueves",
    "sorteo": "Previa",
    "loteria": "NACION",
    "numeros": [
      "8097",
      "0224",
      "4492",
      "7266",
      "7942",
      "2446",
      "3257",
      "9275",
      "9672",
      "4142",
      "1246",
      "0080",
      "5639",
      "7979",
      "7356",
      "6772",
      "1420",
      "8882",
      "2026",
      "6997"
    ],
    "pizarraLink": "https://vivitusuerte.com/pizarra/ciudad"
  },
  {
    "id": "1737670734765-NACION-Primera",
    "fecha": "23/01/2025",
    "dia": "jueves",
    "sorteo": "Primera",
    "loteria": "NACION",
    "numeros": [
      "8120",
      "6634",
      "5049",
      "5914",
      "1980",
      "9407",
      "9960",
      "0579",
      "6917",
      "6521",
      "1635",
      "1809",
      "7267",
      "4709",
      "4921",
      "9912",
      "8580",
      "9743",
      "6438",
      "2466"
    ],
    "pizarraLink": "https://vivitusuerte.com/pizarra/ciudad"
  },
  {
    "id": "1737670734970-NACION-Matutina",
    "fecha": "23/01/2025",
    "dia": "jueves",
    "sorteo": "Matutina",
    "loteria": "NACION",
    "numeros": [
      "5878",
      "4811",
      "3946",
      "3202",
      "9244",
      "7364",
      "4395",
      "0170",
      "9527",
      "1139",
      "7981",
      "3542",
      "2027",
      "7779",
      "3543",
      "7305",
      "8227",
      "0954",
      "4284",
      "5801"
    ],
    "pizarraLink": "https://vivitusuerte.com/pizarra/ciudad"
  },
  {
    "id": "1737670735148-NACION-Vespertina",
    "fecha": "23/01/2025",
    "dia": "jueves",
    "sorteo": "Vespertina",
    "loteria": "NACION",
    "numeros": [
      "7317",
      "2722",
      "6525",
      "4041",
      "0887",
      "2893",
      "1587",
      "8202",
      "7017",
      "5815",
      "6743",
      "4665",
      "7057",
      "3637",
      "6560",
      "6623",
      "2339",
      "7866",
      "2811",
      "0656"
    ],
    "pizarraLink": "https://vivitusuerte.com/pizarra/ciudad"
  },
  {
    "id": "1737670735321-PROVINCIA-Previa",
    "fecha": "23/01/2025",
    "dia": "jueves",
    "sorteo": "Previa",
    "loteria": "PROVINCIA",
    "numeros": [
      "1613",
      "7557",
      "6799",
      "2445",
      "2508",
      "3614",
      "4568",
      "3626",
      "6563",
      "6688",
      "3314",
      "1157",
      "4201",
      "0292",
      "0633",
      "1682",
      "8752",
      "2065",
      "3466",
      "5829"
    ],
    "pizarraLink": "https://vivitusuerte.com/pizarra/provincia"
  },
  {
    "id": "1737670735486-PROVINCIA-Primera",
    "fecha": "23/01/2025",
    "dia": "jueves",
    "sorteo": "Primera",
    "loteria": "PROVINCIA",
    "numeros": [
      "5683",
      "6395",
      "9199",
      "9917",
      "1743",
      "9246",
      "8200",
      "3499",
      "6127",
      "6179",
      "5460",
      "3800",
      "2374",
      "9052",
      "4740",
      "7432",
      "6571",
      "9460",
      "1786",
      "1985"
    ],
    "pizarraLink": "https://vivitusuerte.com/pizarra/provincia"
  },
  {
    "id": "1737670735775-PROVINCIA-Matutina",
    "fecha": "23/01/2025",
    "dia": "jueves",
    "sorteo": "Matutina",
    "loteria": "PROVINCIA",
    "numeros": [
      "3737",
      "8726",
      "2449",
      "1151",
      "2482",
      "8449",
      "4986",
      "9473",
      "5847",
      "9777",
      "2184",
      "3750",
      "3443",
      "8694",
      "6847",
      "4005",
      "6299",
      "8272",
      "4644",
      "0034"
    ],
    "pizarraLink": "https://vivitusuerte.com/pizarra/provincia"
  },
  {
    "id": "1737670735940-PROVINCIA-Vespertina",
    "fecha": "23/01/2025",
    "dia": "jueves",
    "sorteo": "Vespertina",
    "loteria": "PROVINCIA",
    "numeros": [
      "0160",
      "4530",
      "4820",
      "9782",
      "0983",
      "0692",
      "4494",
      "3354",
      "1482",
      "5553",
      "9989",
      "7912",
      "1582",
      "0866",
      "7182",
      "0812",
      "9420",
      "6612",
      "9652",
      "8865"
    ],
    "pizarraLink": "https://vivitusuerte.com/pizarra/provincia"
  },
  {
    "id": "1737670736353-CORDOBA-Previa",
    "fecha": "23/01/2025",
    "dia": "jueves",
    "sorteo": "Previa",
    "loteria": "CORDOBA",
    "numeros": [
      "4861",
      "6136",
      "1886",
      "3797",
      "6266",
      "2906",
      "4234",
      "7863",
      "4923",
      "0186",
      "0607",
      "1039",
      "8598",
      "5725",
      "6064",
      "9070",
      "3753",
      "5252",
      "2801",
      "2661"
    ],
    "pizarraLink": "https://vivitusuerte.com/pizarra/cordoba"
  },
  {
    "id": "1737670736515-CORDOBA-Primera",
    "fecha": "23/01/2025",
    "dia": "jueves",
    "sorteo": "Primera",
    "loteria": "CORDOBA",
    "numeros": [
      "5328",
      "7724",
      "3928",
      "7128",
      "0622",
      "1331",
      "6138",
      "0141",
      "8383",
      "4573",
      "2659",
      "6908",
      "0523",
      "5744",
      "2091",
      "0705",
      "7843",
      "4854",
      "7689",
      "5494"
    ],
    "pizarraLink": "https://vivitusuerte.com/pizarra/cordoba"
  },
  {
    "id": "1737670736689-CORDOBA-Matutina",
    "fecha": "23/01/2025",
    "dia": "jueves",
    "sorteo": "Matutina",
    "loteria": "CORDOBA",
    "numeros": [
      "6292",
      "1504",
      "2679",
      "5966",
      "3562",
      "7421",
      "4285",
      "1600",
      "0689",
      "9390",
      "9616",
      "6757",
      "9671",
      "5254",
      "1128",
      "1847",
      "2499",
      "0970",
      "7038",
      "9443"
    ],
    "pizarraLink": "https://vivitusuerte.com/pizarra/cordoba"
  },
  {
    "id": "1737670736850-CORDOBA-Vespertina",
    "fecha": "23/01/2025",
    "dia": "jueves",
    "sorteo": "Vespertina",
    "loteria": "CORDOBA",
    "numeros": [
      "7478",
      "7197",
      "5429",
      "5760",
      "4251",
      "0504",
      "6219",
      "1231",
      "5565",
      "1325",
      "1316",
      "7473",
      "8846",
      "3640",
      "9204",
      "5248",
      "8940",
      "8044",
      "7006",
      "2382"
    ],
    "pizarraLink": "https://vivitusuerte.com/pizarra/cordoba"
  },
  {
    "id": "1737670737012-SANTA FE-Previa",
    "fecha": "23/01/2025",
    "dia": "jueves",
    "sorteo": "Previa",
    "loteria": "SANTA FE",
    "numeros": [
      "6410",
      "4287",
      "2646",
      "4996",
      "7062",
      "4087",
      "7930",
      "5909",
      "2542",
      "5270",
      "8172",
      "1373",
      "5433",
      "2314",
      "5680",
      "7227",
      "8361",
      "2569",
      "0928",
      "0550"
    ],
    "pizarraLink": "https://vivitusuerte.com/pizarra/santa+fe"
  },
  {
    "id": "1737670737173-SANTA FE-Primera",
    "fecha": "23/01/2025",
    "dia": "jueves",
    "sorteo": "Primera",
    "loteria": "SANTA FE",
    "numeros": [
      "9955",
      "1102",
      "3157",
      "1469",
      "1714",
      "7592",
      "0242",
      "9911",
      "2978",
      "3815",
      "6269",
      "5981",
      "4317",
      "2278",
      "9577",
      "7007",
      "9111",
      "4860",
      "6079",
      "8614"
    ],
    "pizarraLink": "https://vivitusuerte.com/pizarra/santa+fe"
  },
  {
    "id": "1737670737353-SANTA FE-Matutina",
    "fecha": "23/01/2025",
    "dia": "jueves",
    "sorteo": "Matutina",
    "loteria": "SANTA FE",
    "numeros": [
      "6018",
      "2150",
      "1281",
      "3508",
      "6853",
      "5083",
      "5313",
      "5843",
      "2591",
      "0541",
      "5487",
      "7340",
      "1793",
      "9265",
      "8759",
      "8659",
      "5053",
      "5387",
      "8091",
      "3761"
    ],
    "pizarraLink": "https://vivitusuerte.com/pizarra/santa+fe"
  },
  {
    "id": "1737670737513-SANTA FE-Vespertina",
    "fecha": "23/01/2025",
    "dia": "jueves",
    "sorteo": "Vespertina",
    "loteria": "SANTA FE",
    "numeros": [
      "6748",
      "3735",
      "6218",
      "2676",
      "7566",
      "9586",
      "8627",
      "0324",
      "3628",
      "5640",
      "8413",
      "5754",
      "3829",
      "0913",
      "2069",
      "7001",
      "2571",
      "7559",
      "8122",
      "7958"
    ],
    "pizarraLink": "https://vivitusuerte.com/pizarra/santa+fe"
  },
  {
    "id": "1737670737671-ENTRE RIOS-Previa",
    "fecha": "23/01/2025",
    "dia": "jueves",
    "sorteo": "Previa",
    "loteria": "ENTRE RIOS",
    "numeros": [
      "0309",
      "3058",
      "2092",
      "3681",
      "8551",
      "7432",
      "1818",
      "8431",
      "3256",
      "6338",
      "4306",
      "8728",
      "9042",
      "1730",
      "7829",
      "1794",
      "2535",
      "9628",
      "1235",
      "8654"
    ],
    "pizarraLink": "https://vivitusuerte.com/pizarra/entre+rios"
  },
  {
    "id": "1737670737836-ENTRE RIOS-Primera",
    "fecha": "23/01/2025",
    "dia": "jueves",
    "sorteo": "Primera",
    "loteria": "ENTRE RIOS",
    "numeros": [
      "1698",
      "7770",
      "7853",
      "6317",
      "9481",
      "7050",
      "8141",
      "1459",
      "3282",
      "8163",
      "9096",
      "9025",
      "9111",
      "1601",
      "3567",
      "9509",
      "0525",
      "5432",
      "3038",
      "9127"
    ],
    "pizarraLink": "https://vivitusuerte.com/pizarra/entre+rios"
  },
  {
    "id": "1737670737995-ENTRE RIOS-Matutina",
    "fecha": "23/01/2025",
    "dia": "jueves",
    "sorteo": "Matutina",
    "loteria": "ENTRE RIOS",
    "numeros": [
      "2439",
      "8146",
      "9045",
      "2179",
      "9785",
      "4134",
      "5411",
      "6568",
      "2348",
      "0965",
      "5695",
      "6074",
      "2091",
      "3355",
      "6313",
      "0833",
      "0212",
      "1194",
      "6027",
      "2737"
    ],
    "pizarraLink": "https://vivitusuerte.com/pizarra/entre+rios"
  },
  {
    "id": "1737670738157-ENTRE RIOS-Vespertina",
    "fecha": "23/01/2025",
    "dia": "jueves",
    "sorteo": "Vespertina",
    "loteria": "ENTRE RIOS",
    "numeros": [
      "1484",
      "1131",
      "7309",
      "8163",
      "9840",
      "4437",
      "9531",
      "8762",
      "2604",
      "5148",
      "1974",
      "1190",
      "7315",
      "2736",
      "9642",
      "4004",
      "8568",
      "9168",
      "4951",
      "3042"
    ],
    "pizarraLink": "https://vivitusuerte.com/pizarra/entre+rios"
  },
  {
    "id": "1737670738423-MENDOZA-Previa",
    "fecha": "23/01/2025",
    "dia": "jueves",
    "sorteo": "Previa",
    "loteria": "MENDOZA",
    "numeros": [
      "5176",
      "3710",
      "9254",
      "0165",
      "3880",
      "9389",
      "1820",
      "2195",
      "6901",
      "6884",
      "5437",
      "3974",
      "5800",
      "5755",
      "1402",
      "7422",
      "5636",
      "9853",
      "9013",
      "7704"
    ],
    "pizarraLink": "https://vivitusuerte.com/pizarra/mendoza"
  },
  {
    "id": "1737670738587-MENDOZA-Primera",
    "fecha": "23/01/2025",
    "dia": "jueves",
    "sorteo": "Primera",
    "loteria": "MENDOZA",
    "numeros": [
      "0801",
      "2999",
      "9592",
      "7712",
      "0918",
      "6650",
      "9440",
      "6072",
      "3769",
      "4277",
      "6861",
      "3864",
      "8753",
      "3170",
      "7967",
      "5162",
      "4236",
      "2424",
      "7773",
      "9301"
    ],
    "pizarraLink": "https://vivitusuerte.com/pizarra/mendoza"
  },
  {
    "id": "1737670738758-MENDOZA-Matutina",
    "fecha": "23/01/2025",
    "dia": "jueves",
    "sorteo": "Matutina",
    "loteria": "MENDOZA",
    "numeros": [
      "3274",
      "2947",
      "2104",
      "9264",
      "5104",
      "7225",
      "4286",
      "7332",
      "7212",
      "6036",
      "2007",
      "9454",
      "1184",
      "3908",
      "2188",
      "3884",
      "2564",
      "0067",
      "7248",
      "6642"
    ],
    "pizarraLink": "https://vivitusuerte.com/pizarra/mendoza"
  },
  {
    "id": "1737670738914-MENDOZA-Vespertina",
    "fecha": "23/01/2025",
    "dia": "jueves",
    "sorteo": "Vespertina",
    "loteria": "MENDOZA",
    "numeros": [
      "9966",
      "3885",
      "3200",
      "1924",
      "2391",
      "6546",
      "5095",
      "8146",
      "7865",
      "2879",
      "3465",
      "8261",
      "2138",
      "8522",
      "5865",
      "3519",
      "1522",
      "0821",
      "7300",
      "4109"
    ],
    "pizarraLink": "https://vivitusuerte.com/pizarra/mendoza"
  },
  {
    "id": "1737670739072-CORRIENTES-Previa",
    "fecha": "23/01/2025",
    "dia": "jueves",
    "sorteo": "Previa",
    "loteria": "CORRIENTES",
    "numeros": [
      "3898",
      "7309",
      "4906",
      "0474",
      "3593",
      "9014",
      "2098",
      "4150",
      "2900",
      "9452",
      "4263",
      "0604",
      "7108",
      "3182",
      "4125",
      "3839",
      "8314",
      "2468",
      "7173",
      "2523"
    ],
    "pizarraLink": "https://vivitusuerte.com/pizarra/corrientes"
  },
  {
    "id": "1737670740048-CORRIENTES-Primera",
    "fecha": "23/01/2025",
    "dia": "jueves",
    "sorteo": "Primera",
    "loteria": "CORRIENTES",
    "numeros": [
      "9063",
      "0280",
      "9711",
      "0254",
      "1969",
      "5480",
      "9804",
      "9730",
      "2071",
      "5827",
      "2895",
      "7207",
      "6387",
      "0576",
      "6592",
      "4943",
      "1267",
      "9123",
      "9985",
      "2139"
    ],
    "pizarraLink": "https://vivitusuerte.com/pizarra/corrientes"
  },
  {
    "id": "1737670740216-CORRIENTES-Matutina",
    "fecha": "23/01/2025",
    "dia": "jueves",
    "sorteo": "Matutina",
    "loteria": "CORRIENTES",
    "numeros": [
      "5555",
      "9583",
      "1997",
      "1545",
      "0044",
      "1061",
      "8737",
      "8509",
      "9493",
      "0149",
      "4487",
      "5395",
      "1319",
      "5934",
      "5741",
      "3974",
      "5510",
      "9994",
      "6097",
      "5959"
    ],
    "pizarraLink": "https://vivitusuerte.com/pizarra/corrientes"
  },
  {
    "id": "1737670740379-CORRIENTES-Vespertina",
    "fecha": "23/01/2025",
    "dia": "jueves",
    "sorteo": "Vespertina",
    "loteria": "CORRIENTES",
    "numeros": [
      "7216",
      "7744",
      "1093",
      "6837",
      "5289",
      "9870",
      "2168",
      "1610",
      "4886",
      "5445",
      "0706",
      "4311",
      "2411",
      "3678",
      "3418",
      "1157",
      "2877",
      "9065",
      "3645",
      "9142"
    ],
    "pizarraLink": "https://vivitusuerte.com/pizarra/corrientes"
  },
  {
    "id": "1737670740542-CHACO-Previa",
    "fecha": "23/01/2025",
    "dia": "jueves",
    "sorteo": "Previa",
    "loteria": "CHACO",
    "numeros": [
      "3782",
      "4870",
      "9593",
      "4166",
      "1893",
      "1991",
      "8351",
      "2844",
      "8907",
      "8133",
      "0079",
      "1530",
      "4097",
      "2445",
      "0500",
      "2070",
      "9536",
      "1883",
      "4713",
      "4215"
    ],
    "pizarraLink": "https://vivitusuerte.com/pizarra/chaco"
  },
  {
    "id": "1737670740703-CHACO-Primera",
    "fecha": "23/01/2025",
    "dia": "jueves",
    "sorteo": "Primera",
    "loteria": "CHACO",
    "numeros": [
      "6206",
      "4607",
      "2402",
      "2256",
      "8131",
      "7610",
      "9822",
      "1453",
      "7979",
      "5890",
      "8587",
      "5496",
      "0614",
      "5103",
      "8822",
      "9846",
      "5390",
      "4376",
      "6969",
      "4271"
    ],
    "pizarraLink": "https://vivitusuerte.com/pizarra/chaco"
  },
  {
    "id": "1737670740862-CHACO-Matutina",
    "fecha": "23/01/2025",
    "dia": "jueves",
    "sorteo": "Matutina",
    "loteria": "CHACO",
    "numeros": [
      "3205",
      "9860",
      "8699",
      "2164",
      "8263",
      "2819",
      "1895",
      "4675",
      "8385",
      "4650",
      "4063",
      "8635",
      "6775",
      "6675",
      "4279",
      "0365",
      "1169",
      "3680",
      "2190",
      "1829"
    ],
    "pizarraLink": "https://vivitusuerte.com/pizarra/chaco"
  },
  {
    "id": "1737670741022-CHACO-Vespertina",
    "fecha": "23/01/2025",
    "dia": "jueves",
    "sorteo": "Vespertina",
    "loteria": "CHACO",
    "numeros": [
      "2810",
      "5816",
      "4358",
      "6714",
      "5293",
      "7607",
      "4105",
      "2355",
      "2750",
      "5339",
      "3474",
      "3855",
      "2211",
      "5686",
      "3272",
      "7117",
      "8051",
      "3396",
      "0294",
      "9353"
    ],
    "pizarraLink": "https://vivitusuerte.com/pizarra/chaco"
  },
  {
    "id": "1737670741262-MONTEVIDEO-Matutina",
    "fecha": "23/01/2025",
    "dia": "jueves",
    "sorteo": "Matutina",
    "loteria": "MONTEVIDEO",
    "numeros": [
      "5391",
      "4433",
      "3756",
      "3674",
      "9811",
      "7769",
      "4921",
      "0692",
      "9525",
      "1738",
      "7482",
      "3069",
      "2475",
      "7922",
      "3465",
      "7627",
      "8960",
      "0190",
      "4157",
      "5788"
    ],
    "pizarraLink": "https://vivitusuerte.com/pizarra/montevideo"
  }
]